[
  {
    "image": "retreat_sept_15/valley.jpg",
    "location": "Honsur"
  },
  {
    "image": "pondi_sept_15/beach.jpg",
    "location": "Pondicherry"
  },
  {
    "image": "pondi_sept_15/beach_house.jpg",
    "location": "Pondicherry"
  },
  {
    "image": "mahabalipuram_15/sunset.jpg",
    "location": "Mahabalipuram"
  },
  {
    "image": "mahabalipuram_15/shore_temple.jpg",
    "location": "Mahabalipuram"
  },
  {
    "image": "bye_sweden_15/gbg_night.jpg",
    "location": "Gothenburg"
  },
  {
    "image": "bye_sweden_15/overview.jpg",
    "location": "Vann"
  },
  {
    "image": "bye_sweden_15/water.jpg",
    "location": "Vann"
  },
  {
    "image": "IMG_8208.jpg",
    "location": "Helsinki"
  },
  {
    "image": "IMG_2358.jpg",
    "location": "Valkosaari"
  },
  {
    "image": "IMG_0474.jpg",
    "location": "Chicago"
  },
  {
    "image": "IMG_0436.jpg",
    "location": "Chicago"
  },
  {
    "image": "IMG_0430.jpg",
    "location": "Chicago"
  },
  {
    "image": "IMG_0412.jpg",
    "location": "Chicago"
  },
  {
    "image": "IMG_0395.jpg",
    "location": "Chicago"
  },
  {
    "image": "IMG_0315.jpg",
    "location": "Yosemite"
  },
  {
    "image": "IMG_0290.jpg",
    "location": "San Francisco"
  },
  {
    "image": "IMG_0271.jpg",
    "location": "Golden Gate Bridge"
  },
  {
    "image": "twin_peaks.jpg",
    "location": "Twin Peaks"
  },
  {
    "image": "santorini_crater.jpg",
    "location": "Santorini"
  },
  {
    "image": "santorini_coast.jpg",
    "location": "Santorini"
  },
  {
    "image": "crete_sunset.jpg",
    "location": "Crete"
  },
  {
    "image": "chania_sundown.jpg",
    "location": "Chania"
  },
  {
    "image": "chania_sunset.jpg",
    "location": "Chania"
  },
  {
    "image": "georgioupoli.jpg",
    "location": "Georgioupoli"
  },
  {
    "image": "rethimnon.jpg",
    "location": "Rethimnon"
  },
  {
    "image": "elafonisi.jpg",
    "location": "Elafonisi"
  },
  {
    "image": "BSgudnaIAAAU8Ep.jpg",
    "location": "Gothenburg"
  },
  {
    "image": "BSguSeLIEAArywo.jpg",
    "location": "Melbourne",
    "date": "2013-08-25T11:40:09Z"
  },
  {
    "image": "BSguKfhIcAA-lEd.jpg",
    "location": "Melbourne"
  },
  {
    "image": "BSguCmlIYAAk2Rx.jpg",
    "location": "Melbourne"
  },
  {
    "image": "brewh.jpg",
    "location": "Mumbai"
  },
  {
    "image": "qr9cd.jpg",
    "location": "Delhi"
  },
  {
    "image": "ropta.jpg",
    "location": "Taj Mahal"
  },
  {
    "image": "w43ks.jpg",
    "location": "Delhi"
  },
  {
    "image": "v35pg.jpg",
    "location": "Delhi"
  },
  {
    "image": "2z3sl.jpg",
    "location": "Mumbai"
  },
  {
    "image": "dx2g.jpg",
    "location": "Anjuna Beach"
  },
  {
    "image": "z59ct.jpg",
    "location": "Anjuna Beach"
  },
  {
    "image": "durvp.jpg",
    "location": "Goa"
  },
  {
    "image": "53ylja.jpg",
    "location": "Ruby Skye"
  },
  {
    "image": "46kbz.jpg",
    "location": "San Francisco"
  },
  {
    "image": "46057365.jpg",
    "location": "Krakow"
  },
  {
    "image": "r1pgbn.jpg",
    "location": "Baltic Sea"
  },
  {
    "image": "4zzhfr.jpg",
    "location": "Helsinki"
  },
  {
    "image": "r0lph.jpg",
    "location": "Stockholm"
  },
  {
    "image": "t1wqg.jpg",
    "location": "Stockholm"
  },
  {
    "image": "rlbzw.jpg",
    "location": "Helsinki"
  },
  {
    "image": "86417529.jpg",
    "location": "California"
  },
  {
    "image": "8bxtt.jpg",
    "location": "Bay Area"
  },
  {
    "image": "2frwe.jpg",
    "location": "Reeperbahn"
  },
  {
    "image": "zkqp.jpg",
    "location": "Hamburg"
  },
  {
    "image": "462954579.jpg",
    "location": "Helsinki"
  },
  {
    "image": "463010735.jpg",
    "location": "Helsinki"
  },
  {
    "image": "bidho.jpg",
    "location": "Gamla Stan"
  },
  {
    "image": "431691548.jpg",
    "location": "Leppävaara"
  },
  {
    "image": "g29hs.jpg",
    "location": "sfo"
  },
  {
    "image": "423788129.jpg",
    "location": "San Francisco"
  },
  {
    "image": "v2sby.jpg",
    "location": "Trafalgar Square"
  },
  {
    "image": "os9mo.jpg",
    "location": "London"
  },
  {
    "image": "hkpdu.jpg",
    "location": "London"
  },
  {
    "image": "4o9af.jpg",
    "location": "London"
  },
  {
    "image": "cqgeeo.jpg",
    "location": "Paris"
  },
  {
    "image": "k0fig.jpg",
    "location": "Ibiza"
  },
  {
    "image": "4leps.jpg",
    "location": "Ibiza"
  },
  {
    "image": "yuau.jpg",
    "location": "Ibiza"
  },
  {
    "image": "ousup.jpg",
    "location": "Ibiza"
  },
  {
    "image": "pz2zn.jpg",
    "location": "Ibiza"
  },
  {
    "image": "kksa.jpg",
    "location": "Ibiza"
  },
  {
    "image": "w3ojs.jpg",
    "location": "Barcelona"
  },
  {
    "image": "pcjyqp.jpg",
    "location": "Monte Carlo"
  },
  {
    "image": "qd1zg.jpg",
    "location": "Monaco"
  },
  {
    "image": "8smc.jpg",
    "location": "Monaco"
  },
  {
    "image": "o4zmw.jpg",
    "location": "Nice"
  },
  {
    "image": "3p7m.jpg",
    "location": "Rome"
  },
  {
    "image": "j80yj.jpg",
    "location": "Switzerland"
  },
  {
    "image": "pq4s.jpg",
    "location": "Rome"
  },
  {
    "image": "ufsmc.jpg",
    "location": "Switzerland"
  },
  {
    "image": "u6nic.jpg",
    "location": "Oktoberfest 2011"
  },
  {
    "image": "8z5og.jpg",
    "location": "Berlin"
  },
  {
    "image": "a3uky.jpg",
    "location": "Berlin"
  },
  {
    "image": "399127953.jpg",
    "location": "Brussels"
  },
  {
    "image": "v23bn.jpg",
    "location": "Antwerp"
  },
  {
    "image": "xagr.jpg",
    "location": "Amsterdam"
  },
  {
    "image": "md9wcg.jpg",
    "location": "Hamburg"
  },
  {
    "image": "olib.jpg",
    "location": "Stockholm"
  },
  {
    "image": "qvowf.jpg",
    "location": "Stockholm"
  },
  {
    "image": "389753129.jpg",
    "location": "Porvoo"
  },
  {
    "image": "348812713.jpg",
    "location": "Porvoo"
  },
  {
    "image": "348524110.jpg",
    "location": "Kamppi"
  },
  {
    "image": "347778827.jpg",
    "location": "Kallio"
  },
  {
    "image": "347899542.jpg",
    "location": "Helsinki"
  },
  {
    "image": "347901753.jpg",
    "location": "Porvoo"
  },
  {
    "image": "348056518.jpg",
    "location": "Porvoo"
  },
  {
    "image": "348057983.jpg",
    "location": "Kaunisaari"
  },
  {
    "image": "347903890.jpg",
    "location": "Kaunisaari"
  },
  {
    "image": "346683264.jpg",
    "location": "32000ft"
  },
  {
    "image": "348054364.jpg",
    "location": "Paris"
  },
  {
    "image": "348051787.jpg",
    "location": "Santa Cruz"
  },
  {
    "image": "5toi.jpg",
    "location": "San Pedro"
  },
  {
    "image": "5nc0x.jpg",
    "location": "Isle Ippocampo"
  },
  {
    "image": "Ft6Ui.jpg",
    "location": "Isle Ippocampo"
  },
  {
    "image": "KCTEx.jpg",
    "location": "HEL"
  },
  {
    "image": "0iPbW.jpg",
    "location": "Helsinki"
  }
]
